odoo/addons/delivery_ups_oca/README.rst
odoo/addons/delivery_ups_oca/__init__.py
odoo/addons/delivery_ups_oca/__manifest__.py
odoo/addons/delivery_ups_oca/data/stock_package_type_data.xml
odoo/addons/delivery_ups_oca/i18n/delivery_ups_oca.pot
odoo/addons/delivery_ups_oca/i18n/it.po
odoo/addons/delivery_ups_oca/models/__init__.py
odoo/addons/delivery_ups_oca/models/delivery_carrier.py
odoo/addons/delivery_ups_oca/models/stock_package_type.py
odoo/addons/delivery_ups_oca/models/stock_picking.py
odoo/addons/delivery_ups_oca/models/ups_request.py
odoo/addons/delivery_ups_oca/readme/CONFIGURE.md
odoo/addons/delivery_ups_oca/readme/CONTRIBUTORS.md
odoo/addons/delivery_ups_oca/readme/DESCRIPTION.md
odoo/addons/delivery_ups_oca/readme/ROADMAP.md
odoo/addons/delivery_ups_oca/readme/USAGE.md
odoo/addons/delivery_ups_oca/static/description/icon.png
odoo/addons/delivery_ups_oca/static/description/index.html
odoo/addons/delivery_ups_oca/tests/__init__.py
odoo/addons/delivery_ups_oca/tests/test_delivery_ups.py
odoo/addons/delivery_ups_oca/views/delivery_carrier_view.xml
odoo/addons/delivery_ups_oca/views/stock_picking_view.xml
odoo_addon_delivery_ups_oca-17.0.1.0.0.3.dist-info/METADATA
odoo_addon_delivery_ups_oca-17.0.1.0.0.3.dist-info/WHEEL
odoo_addon_delivery_ups_oca-17.0.1.0.0.3.dist-info/top_level.txt
odoo_addon_delivery_ups_oca-17.0.1.0.0.3.dist-info/RECORD
