Metadata-Version: 2.1
Name: odoo-addon-delivery_ups_oca
Version: 17.0.1.0.0.3
Requires-Python: >=3.10
Requires-Dist: odoo-addon-delivery_package_number>=17.0dev,<17.1dev
Requires-Dist: odoo-addon-delivery_price_method>=17.0dev,<17.1dev
Requires-Dist: odoo-addon-delivery_state>=17.0dev,<17.1dev
Requires-Dist: odoo>=17.0a,<17.1dev
Summary: Integrate UPS webservice
Home-page: https://github.com/OCA/delivery-carrier
License: AGPL-3
Author: Hunki Enterprises BV, Tecnativa, ForgeFlow, Odoo Community Association (OCA)
Author-email: support@odoo-community.org
Classifier: Programming Language :: Python
Classifier: Framework :: Odoo
Classifier: Framework :: Odoo :: 17.0
Classifier: License :: OSI Approved :: GNU Affero General Public License v3
Classifier: Development Status :: 4 - Beta
